{
  "project_info": {
    "project_number": "385864340445",
    "project_id": "smartstudy-60a73",
    "storage_bucket": "smartstudy-60a73.firebasestorage.app"
  },
  "client": [
    {
      "client_info": {
        "mobilesdk_app_id": "1:385864340445:android:a0a1132a0ea89ddece1c34",
        "android_client_info": {
          "package_name": "com.anonymous.smartstudyquizgenerator"
        }
      },
      "oauth_client": [
        {
          "client_id": "385864340445-hvmsu5fno111jl9ahp6ea1lubhvhc4sp.apps.googleusercontent.com",
          "client_type": 3
        }
      ],
      "api_key": [
        {
          "current_key": "AIzaSyDHAb_IkFJbBkZavFckEWDnbvBAPwgsD0E"
        }
      ],
      "services": {
        "appinvite_service": {
          "other_platform_oauth_client": [
            {
              "client_id": "385864340445-hvmsu5fno111jl9ahp6ea1lubhvhc4sp.apps.googleusercontent.com",
              "client_type": 3
            }
          ]
        }
      }
    }
  ],
  "configuration_version": "1"
}